ksubscribe/__init__.py
ksubscribe-1.0.8.dist-info/LICENSE
ksubscribe-1.0.8.dist-info/METADATA
ksubscribe-1.0.8.dist-info/WHEEL
ksubscribe-1.0.8.dist-info/top_level.txt
ksubscribe-1.0.8.dist-info/RECORD
